[
  {
    "name": "Overclock Geforce 8800 GTX",
    "price": 150,
    "targetCard": "Geforce 8800 GTX"
  },
  {
    "name": "Overclock Radeon HD 4870",
    "price": 200,
    "targetCard": "Radeon HD 4870"
  },
  {
    "name": "Overclock GTX 295",
    "price": 750,
    "targetCard": "GTX 295"
  },
  {
    "name": "Overclock GTX 480",
    "price": 2000,
    "targetCard": "GTX 480"
  },
  {
    "name": "Overclock GTX 580",
    "price": 7000,
    "targetCard": "GTX 580"
  },
  {
    "name": "Overclock GTX 690",
    "price": 20000,
    "targetCard": "GTX 690"
  },
  {
    "name": "Overclock Radeon R9 295X2",
    "price": 39000,
    "targetCard": "Radeon R9 295X2"
  },
  {
    "name": "Overclock GTX Titan Z",
    "price": 55000,
    "targetCard": "GTX Titan Z"
  },
  {
    "name": "Overclock GTX Titan X",
    "price": 190000,
    "targetCard": "GTX Titan X"
  },
  {
    "name": "Overclock RX Vega 56",
    "price": 500000,
    "targetCard": "RX Vega 56"
  },
  {
    "name": "Overclock GTX Titan V",
    "price": 2500000,
    "targetCard": "GTX Titan V"
  }
]